{
  "kind": "Config",
  "apiVersion": "v1beta3",
  "metadata": {},
  "items": [
    {
      "apiVersion": "v1beta2",
      "containerPort": 8080,
      "creationTimestamp": null,
      "id": "jenkins",
      "kind": "Service",
      "port": 5002,
      "selector": {
        "name": "jenkinspod"
      }
    },
    {
      "apiVersion": "v1beta1",
      "kind": "DeploymentConfig",
      "metadata": {
        "name": "jenkins"
      },
      "template": {
        "controllerTemplate": {
          "podTemplate": {
            "desiredState": {
              "manifest": {
                "containers": [
                  {
                    "image": "openshift/jenkins-1-centos",
                    "name": "jenkins-container",
                    "ports": [
                      {
                        "containerPort": 8080,
                        "protocol": "TCP"
                      }
                    ]
                  }
                ],
                "version": "v1beta1"
              },
              "restartpolicy": {}
            },
            "labels": {
              "name": "jenkinspod"
            }
          },
          "replicaSelector": {
            "name": "jenkinspod"
          },
          "replicas": 1
        },
        "strategy": {
          "type": "Recreate"
        }
      },
      "triggers": [
        {
          "type": "ConfigChange"
        }
      ]
    }
  ]
}