{
    "items": [
        {
            "level": "Info",
            "locator": "namespace/e2e-kubectl-3271 pod/without-label uid/e185b70c-ea3e-4600-850a-b2370a729a73",
            "message": "constructed/pod-lifecycle-constructor reason/Created",
            "tempSource": "PodState",
            "tempStructuredLocator": {
                "type": "Pod",
                "keys": {
                    "namespace": "e2e-kubectl-3271",
                    "pod": "without-label",
                    "uid": "e185b70c-ea3e-4600-850a-b2370a729a73"
                }
            },
            "tempStructuredMessage": {
                "reason": "Created",
                "cause": "",
                "humanMessage": "",
                "annotations": {
                    "constructed": "pod-lifecycle-constructor",
                    "reason": "Created"
                }
            },
            "from": "2022-03-07T18:41:46Z",
            "to": "2022-03-07T18:41:46Z"
        },
        {
            "level": "Info",
            "locator": "namespace/e2e-kubectl-3271 pod/without-label uid/e185b70c-ea3e-4600-850a-b2370a729a73 container/without-label",
            "message": "constructed/pod-lifecycle-constructor reason/ContainerWait missed real \"ContainerWait\"",
            "tempSource": "PodState",
            "tempStructuredLocator": {
                "type": "Container",
                "keys": {
                    "container": "without-label",
                    "namespace": "e2e-kubectl-3271",
                    "pod": "without-label",
                    "uid": "e185b70c-ea3e-4600-850a-b2370a729a73"
                }
            },
            "tempStructuredMessage": {
                "reason": "ContainerWait",
                "cause": "",
                "humanMessage": "missed real \"ContainerWait\"",
                "annotations": {
                    "constructed": "pod-lifecycle-constructor",
                    "reason": "ContainerWait"
                }
            },
            "from": "2022-03-07T18:41:46Z",
            "to": "2022-03-07T18:41:52Z"
        },
        {
            "level": "Info",
            "locator": "namespace/e2e-kubectl-3271 pod/without-label uid/e185b70c-ea3e-4600-850a-b2370a729a73",
            "message": "constructed/pod-lifecycle-constructor node/ip-10-0-141-9.us-west-2.compute.internal reason/Scheduled",
            "tempSource": "PodState",
            "tempStructuredLocator": {
                "type": "Pod",
                "keys": {
                    "namespace": "e2e-kubectl-3271",
                    "pod": "without-label",
                    "uid": "e185b70c-ea3e-4600-850a-b2370a729a73"
                }
            },
            "tempStructuredMessage": {
                "reason": "Scheduled",
                "cause": "",
                "humanMessage": "",
                "annotations": {
                    "constructed": "pod-lifecycle-constructor",
                    "node": "ip-10-0-141-9.us-west-2.compute.internal",
                    "reason": "Scheduled"
                }
            },
            "from": "2022-03-07T18:41:46Z",
            "to": "2022-03-07T18:41:54Z"
        },
        {
            "level": "Info",
            "locator": "namespace/e2e-kubectl-3271 pod/without-label uid/e185b70c-ea3e-4600-850a-b2370a729a73 container/without-label",
            "message": "constructed/pod-lifecycle-constructor reason/NotReady missed real \"NotReady\"",
            "tempSource": "PodState",
            "tempStructuredLocator": {
                "type": "Container",
                "keys": {
                    "container": "without-label",
                    "namespace": "e2e-kubectl-3271",
                    "pod": "without-label",
                    "uid": "e185b70c-ea3e-4600-850a-b2370a729a73"
                }
            },
            "tempStructuredMessage": {
                "reason": "NotReady",
                "cause": "",
                "humanMessage": "missed real \"NotReady\"",
                "annotations": {
                    "constructed": "pod-lifecycle-constructor",
                    "reason": "NotReady"
                }
            },
            "from": "2022-03-07T18:41:52Z",
            "to": "2022-03-07T18:41:52Z"
        },
        {
            "level": "Info",
            "locator": "namespace/e2e-kubectl-3271 pod/without-label uid/e185b70c-ea3e-4600-850a-b2370a729a73 container/without-label",
            "message": "cause/ constructed/pod-lifecycle-constructor duration/6.00s reason/ContainerStart",
            "tempSource": "PodState",
            "tempStructuredLocator": {
                "type": "Container",
                "keys": {
                    "container": "without-label",
                    "namespace": "e2e-kubectl-3271",
                    "pod": "without-label",
                    "uid": "e185b70c-ea3e-4600-850a-b2370a729a73"
                }
            },
            "tempStructuredMessage": {
                "reason": "ContainerStart",
                "cause": "",
                "humanMessage": "",
                "annotations": {
                    "cause": "",
                    "constructed": "pod-lifecycle-constructor",
                    "duration": "6.00s",
                    "reason": "ContainerStart"
                }
            },
            "from": "2022-03-07T18:41:52Z",
            "to": "2022-03-07T18:41:54Z"
        },
        {
            "level": "Info",
            "locator": "namespace/e2e-kubectl-3271 pod/without-label uid/e185b70c-ea3e-4600-850a-b2370a729a73 container/without-label",
            "message": "constructed/pod-lifecycle-constructor reason/Ready",
            "tempSource": "PodState",
            "tempStructuredLocator": {
                "type": "Container",
                "keys": {
                    "container": "without-label",
                    "namespace": "e2e-kubectl-3271",
                    "pod": "without-label",
                    "uid": "e185b70c-ea3e-4600-850a-b2370a729a73"
                }
            },
            "tempStructuredMessage": {
                "reason": "Ready",
                "cause": "",
                "humanMessage": "",
                "annotations": {
                    "constructed": "pod-lifecycle-constructor",
                    "reason": "Ready"
                }
            },
            "from": "2022-03-07T18:41:52Z",
            "to": "2022-03-07T18:41:54Z"
        }
    ]
}
